system_calls/__init__.py
system_calls/architectures_in_kernel.py
system_calls/linux_version.py
system_calls/tables/alpha.py
system_calls/tables/arc.py
system_calls/tables/arm.py
system_calls/tables/arm64.py
system_calls/tables/armoabi.py
system_calls/tables/avr32.py
system_calls/tables/blackfin.py
system_calls/tables/c6x.py
system_calls/tables/cris.py
system_calls/tables/csky.py
system_calls/tables/frv.py
system_calls/tables/h8300.py
system_calls/tables/hexagon.py
system_calls/tables/i386.py
system_calls/tables/ia64.py
system_calls/tables/loongarch64.py
system_calls/tables/m32r.py
system_calls/tables/m68k.py
system_calls/tables/metag.py
system_calls/tables/microblaze.py
system_calls/tables/mips64.py
system_calls/tables/mips64n32.py
system_calls/tables/mipso32.py
system_calls/tables/mn10300.py
system_calls/tables/names.py
system_calls/tables/nds32.py
system_calls/tables/nios2.py
system_calls/tables/openrisc.py
system_calls/tables/parisc.py
system_calls/tables/parisc64.py
system_calls/tables/powerpc.py
system_calls/tables/powerpc64.py
system_calls/tables/riscv32.py
system_calls/tables/riscv64.py
system_calls/tables/s390.py
system_calls/tables/s390x.py
system_calls/tables/score.py
system_calls/tables/sh.py
system_calls/tables/sh64.py
system_calls/tables/sparc.py
system_calls/tables/sparc64.py
system_calls/tables/tile.py
system_calls/tables/tile64.py
system_calls/tables/unicore32.py
system_calls/tables/x32.py
system_calls/tables/x86_64.py
system_calls/tables/xtensa.py
system_calls/tests/test_syscalls.py
system_calls-6.17.0.data/data/share/man/man1/syscall.1
system_calls-6.17.0.data/scripts/syscall
system_calls-6.17.0.dist-info/licenses/LICENSE
system_calls-6.17.0.dist-info/METADATA
system_calls-6.17.0.dist-info/WHEEL
system_calls-6.17.0.dist-info/top_level.txt
system_calls-6.17.0.dist-info/RECORD
