Metadata-Version: 2.4
Name: system-calls
Version: 6.17.0
Summary: Python module to check for system call number/name andavailability
Home-page: https://github.com/hrw/syscalls-table
Author: Marcin Juszkiewicz
Author-email: marcin-python@juszkiewicz.com.pl
Project-URL: Bug Tracker, https://github.com/hrw/syscalls-table/issues
Classifier: Programming Language :: Python :: 3
Classifier: License :: OSI Approved :: MIT License
Classifier: Operating System :: POSIX :: Linux
Requires-Python: >=3.6
License-File: LICENSE
Dynamic: author
Dynamic: author-email
Dynamic: classifier
Dynamic: description
Dynamic: description-content-type
Dynamic: home-page
Dynamic: license-file
Dynamic: project-url
Dynamic: requires-python
Dynamic: summary
